[{
  "price": 32.599,
  "side": "BUY",
  "strategy": "Trend from seasonal decompositon",
  "symbol": "SOL",
  "timestamp": {
    "$date": {
      "$numberLong": "1664301633000"
    }
  }
},{
  "price": 32.112,
  "side": "SELL",
  "strategy": "Trend from seasonal decompositon",
  "symbol": "SOL",
  "timestamp": {
    "$date": {
      "$numberLong": "1664348888000"
    }
  }
},{
  "price": 33.331,
  "side": "BUY",
  "strategy": "Trend from seasonal decompositon",
  "symbol": "SOL",
  "timestamp": {
    "$date": {
      "$numberLong": "1664438499000"
    }
  }
},{
  "price": 32.821,
  "side": "SELL",
  "strategy": "Trend from seasonal decompositon",
  "symbol": "SOL",
  "timestamp": {
    "$date": {
      "$numberLong": "1664607662000"
    }
  }
},{
  "price": 32.888,
  "side": "BUY",
  "strategy": "Trend from seasonal decompositon",
  "symbol": "SOL",
  "timestamp": {
    "$date": {
      "$numberLong": "1664845464000"
    }
  }
},{
  "side": "SELL",
  "price": 32.953,
  "timestamp": {
    "$date": {
      "$numberLong": "1665349248000"
    }
  },
  "strategy": "Trend from seasonal decompositon",
  "symbol": "SOL"
},{
  "side": "BUY",
  "price": 33.299,
  "timestamp": {
    "$date": {
      "$numberLong": "1665363643000"
    }
  },
  "strategy": "Trend from seasonal decompositon",
  "symbol": "SOL"
},{
  "side": "SELL",
  "price": 32.484,
  "timestamp": {
    "$date": {
      "$numberLong": "1665435652000"
    }
  },
  "strategy": "Trend from seasonal decompositon",
  "symbol": "SOL"
},{
  "side": "BUY",
  "price": 30.158,
  "timestamp": {
    "$date": {
      "$numberLong": "1665965528000"
    }
  },
  "strategy": "Trend from seasonal decompositon",
  "symbol": "SOL"
},{
  "side": "SELL",
  "price": 29.89,
  "timestamp": {
    "$date": {
      "$numberLong": "1666141278000"
    }
  },
  "strategy": "Trend from seasonal decompositon",
  "symbol": "SOL"
},{
  "side": "BUY",
  "price": 27.996,
  "timestamp": {
    "$date": {
      "$numberLong": "1666454456000"
    }
  },
  "strategy": "Trend from seasonal decompositon",
  "symbol": "SOL"
},{
  "side": "SELL",
  "price": 28.454,
  "timestamp": {
    "$date": {
      "$numberLong": "1666677656000"
    }
  },
  "strategy": "Trend from seasonal decompositon",
  "symbol": "SOL"
},{
  "side": "BUY",
  "price": 30.976,
  "timestamp": {
    "$date": {
      "$numberLong": "1666731656000"
    }
  },
  "strategy": "Trend from seasonal decompositon",
  "symbol": "SOL"
},{
  "side": "SELL",
  "price": 30.653,
  "timestamp": {
    "$date": {
      "$numberLong": "1666929655000"
    }
  },
  "strategy": "Trend from seasonal decompositon",
  "symbol": "SOL"
},{
  "side": "BUY",
  "price": 32.896,
  "timestamp": {
    "$date": {
      "$numberLong": "1667016055000"
    }
  },
  "strategy": "Trend from seasonal decompositon",
  "symbol": "SOL"
},{
  "side": "SELL",
  "price": 32.34,
  "timestamp": {
    "$date": {
      "$numberLong": "1667160055000"
    }
  },
  "strategy": "Trend from seasonal decompositon",
  "symbol": "SOL"
},{
  "side": "BUY",
  "price": 32.965,
  "timestamp": {
    "$date": {
      "$numberLong": "1667232055000"
    }
  },
  "strategy": "Trend from seasonal decompositon",
  "symbol": "SOL"
},{
  "side": "SELL",
  "price": 32.565,
  "timestamp": {
    "$date": {
      "$numberLong": "1667311255000"
    }
  },
  "strategy": "Trend from seasonal decompositon",
  "symbol": "SOL"
},{
  "side": "BUY",
  "price": 31.936,
  "timestamp": {
    "$date": {
      "$numberLong": "1667469651000"
    }
  },
  "strategy": "Trend from seasonal decompositon",
  "symbol": "SOL"
},{
  "side": "BUY",
  "price": 31.486,
  "timestamp": {
    "$date": {
      "$numberLong": "1667487650000"
    }
  },
  "strategy": "Trend from seasonal decompositon",
  "symbol": "SOL"
},{
  "side": "BUY",
  "price": 31.184,
  "timestamp": {
    "$date": {
      "$numberLong": "1667523655000"
    }
  },
  "strategy": "Trend from seasonal decompositon",
  "symbol": "SOL"
},{
  "side": "SELL",
  "price": 32.346,
  "timestamp": {
    "$date": {
      "$numberLong": "1667782855000"
    }
  },
  "strategy": "Trend from seasonal decompositon",
  "symbol": "SOL"
},{
  "side": "BUY",
  "price": 17.003,
  "timestamp": {
    "$date": {
      "$numberLong": "1668106849000"
    }
  },
  "strategy": "Trend from seasonal decompositon",
  "symbol": "SOL"
},{
  "side": "BUY",
  "price": 16.283,
  "timestamp": {
    "$date": {
      "$numberLong": "1668139255000"
    }
  },
  "strategy": "Trend from seasonal decompositon",
  "symbol": "SOL"
},{
  "side": "SELL",
  "price": 15.161,
  "timestamp": {
    "$date": {
      "$numberLong": "1668236454000"
    }
  },
  "strategy": "Trend from seasonal decompositon",
  "symbol": "SOL"
},{
  "side": "BUY",
  "price": 13.941,
  "timestamp": {
    "$date": {
      "$numberLong": "1668477655000"
    }
  },
  "strategy": "Trend from seasonal decompositon",
  "symbol": "SOL"
},{
  "side": "SELL",
  "price": 14.179,
  "timestamp": {
    "$date": {
      "$numberLong": "1668625254000"
    }
  },
  "strategy": "Trend from seasonal decompositon",
  "symbol": "SOL"
},{
  "side": "BUY",
  "price": 13.615,
  "timestamp": {
    "$date": {
      "$numberLong": "1668758453000"
    }
  },
  "strategy": "Trend from seasonal decompositon",
  "symbol": "SOL"
},{
  "side": "BUY",
  "price": 12.865,
  "timestamp": {
    "$date": {
      "$numberLong": "1669179655000"
    }
  },
  "strategy": "Trend from seasonal decompositon",
  "symbol": "SOL"
},{
  "side": "SELL",
  "price": 14.042,
  "timestamp": {
    "$date": {
      "$numberLong": "1669399255000"
    }
  },
  "strategy": "Trend from seasonal decompositon",
  "symbol": "SOL"
},{
  "side": "BUY",
  "price": 14.662,
  "timestamp": {
    "$date": {
      "$numberLong": "1669467655000"
    }
  },
  "strategy": "Trend from seasonal decompositon",
  "symbol": "SOL"
},{
  "side": "SELL",
  "price": 14.349,
  "timestamp": {
    "$date": {
      "$numberLong": "1669550455000"
    }
  },
  "strategy": "Trend from seasonal decompositon",
  "symbol": "SOL"
},{
  "side": "BUY",
  "price": 13.378,
  "timestamp": {
    "$date": {
      "$numberLong": "1669672848000"
    }
  },
  "strategy": "Trend from seasonal decompositon",
  "symbol": "SOL"
},{
  "side": "BUY",
  "price": 13.401,
  "timestamp": {
    "$date": {
      "$numberLong": "1669741255000"
    }
  },
  "strategy": "Trend from seasonal decompositon",
  "symbol": "SOL"
},{
  "side": "SELL",
  "price": 13.471,
  "timestamp": {
    "$date": {
      "$numberLong": "1669957255000"
    }
  },
  "strategy": "Trend from seasonal decompositon",
  "symbol": "SOL"
},{
  "side": "BUY",
  "price": 13.636,
  "timestamp": {
    "$date": {
      "$numberLong": "1670047254000"
    }
  },
  "strategy": "Trend from seasonal decompositon",
  "symbol": "SOL"
},{
  "side": "SELL",
  "price": 13.478,
  "timestamp": {
    "$date": {
      "$numberLong": "1670115655000"
    }
  },
  "strategy": "Trend from seasonal decompositon",
  "symbol": "SOL"
},{
  "side": "BUY",
  "price": 13.902,
  "timestamp": {
    "$date": {
      "$numberLong": "1670212854000"
    }
  },
  "strategy": "Trend from seasonal decompositon",
  "symbol": "SOL"
},{
  "side": "SELL",
  "price": 13.684,
  "timestamp": {
    "$date": {
      "$numberLong": "1670428854000"
    }
  },
  "strategy": "Trend from seasonal decompositon",
  "symbol": "SOL"
},{
  "side": "BUY",
  "price": 13.454,
  "timestamp": {
    "$date": {
      "$numberLong": "1670468449000"
    }
  },
  "strategy": "Trend from seasonal decompositon",
  "symbol": "SOL"
},{
  "side": "BUY",
  "price": 13.654,
  "timestamp": {
    "$date": {
      "$numberLong": "1670565655000"
    }
  },
  "strategy": "Trend from seasonal decompositon",
  "symbol": "SOL"
},{
  "side": "SELL",
  "price": 13.601,
  "timestamp": {
    "$date": {
      "$numberLong": "1670670055000"
    }
  },
  "strategy": "Trend from seasonal decompositon",
  "symbol": "SOL"
},{
  "side": "BUY",
  "price": 13.631,
  "timestamp": {
    "$date": {
      "$numberLong": "1670760055000"
    }
  },
  "strategy": "Trend from seasonal decompositon",
  "symbol": "SOL"
},{
  "side": "SELL",
  "price": 12.95,
  "timestamp": {
    "$date": {
      "$numberLong": "1670817655000"
    }
  },
  "strategy": "Trend from seasonal decompositon",
  "symbol": "SOL"
},{
  "side": "BUY",
  "price": 13.596,
  "timestamp": {
    "$date": {
      "$numberLong": "1670954452000"
    }
  },
  "strategy": "Trend from seasonal decompositon",
  "symbol": "SOL"
},{
  "side": "SELL",
  "price": 14.003,
  "timestamp": {
    "$date": {
      "$numberLong": "1671145255000"
    }
  },
  "strategy": "Trend from seasonal decompositon",
  "symbol": "SOL"
},{
  "side": "BUY",
  "price": 12.352,
  "timestamp": {
    "$date": {
      "$numberLong": "1671361249000"
    }
  },
  "strategy": "Trend from seasonal decompositon",
  "symbol": "SOL"
},{
  "side": "BUY",
  "price": 12.311,
  "timestamp": {
    "$date": {
      "$numberLong": "1671375655000"
    }
  },
  "strategy": "Trend from seasonal decompositon",
  "symbol": "SOL"
},{
  "side": "SELL",
  "price": 12.279,
  "timestamp": {
    "$date": {
      "$numberLong": "1671451261000"
    }
  },
  "strategy": "Trend from seasonal decompositon",
  "symbol": "SOL"
},{
  "side": "BUY",
  "price": 12.213,
  "timestamp": {
    "$date": {
      "$numberLong": "1671570055000"
    }
  },
  "strategy": "Trend from seasonal decompositon",
  "symbol": "SOL"
},{
  "side": "SELL",
  "price": 12.089,
  "timestamp": {
    "$date": {
      "$numberLong": "1671706856000"
    }
  },
  "strategy": "Trend from seasonal decompositon",
  "symbol": "SOL"
},{
  "side": "BUY",
  "price": 11.893,
  "timestamp": {
    "$date": {
      "$numberLong": "1671789650000"
    }
  },
  "strategy": "Trend from seasonal decompositon",
  "symbol": "SOL"
},{
  "side": "BUY",
  "price": 11.449,
  "timestamp": {
    "$date": {
      "$numberLong": "1671944447000"
    }
  },
  "strategy": "Trend from seasonal decompositon",
  "symbol": "SOL"
},{
  "side": "BUY",
  "price": 11.413,
  "timestamp": {
    "$date": {
      "$numberLong": "1672005655000"
    }
  },
  "strategy": "Trend from seasonal decompositon",
  "symbol": "SOL"
},{
  "side": "SELL",
  "price": 11.438,
  "timestamp": {
    "$date": {
      "$numberLong": "1672027253000"
    }
  },
  "strategy": "Trend from seasonal decompositon",
  "symbol": "SOL"
},{
  "side": "BUY",
  "price": 11.205,
  "timestamp": {
    "$date": {
      "$numberLong": "1672138855000"
    }
  },
  "strategy": "Trend from seasonal decompositon",
  "symbol": "SOL"
},{
  "side": "BUY",
  "price": 11.051,
  "timestamp": {
    "$date": {
      "$numberLong": "1672146050000"
    }
  },
  "strategy": "Trend from seasonal decompositon",
  "symbol": "SOL"
},{
  "side": "BUY",
  "price": 11.831,
  "timestamp": {
    "$date": {
      "$numberLong": "1672750857000"
    }
  },
  "strategy": "Trend from seasonal decompositon",
  "symbol": "SOL"
},{
  "side": "SELL",
  "price": 13.221,
  "timestamp": {
    "$date": {
      "$numberLong": "1672923656000"
    }
  },
  "strategy": "Trend from seasonal decompositon",
  "symbol": "SOL"
},{
  "side": "BUY",
  "price": 13.197,
  "timestamp": {
    "$date": {
      "$numberLong": "1672995655000"
    }
  },
  "strategy": "Trend from seasonal decompositon",
  "symbol": "SOL"
},{
  "side": "SELL",
  "price": 13.202,
  "timestamp": {
    "$date": {
      "$numberLong": "1673028056000"
    }
  },
  "strategy": "Trend from seasonal decompositon",
  "symbol": "SOL"
},{
  "side": "BUY",
  "price": 13.189,
  "timestamp": {
    "$date": {
      "$numberLong": "1673096455000"
    }
  },
  "strategy": "Trend from seasonal decompositon",
  "symbol": "SOL"
},{
  "side": "SELL",
  "price": 13.345,
  "timestamp": {
    "$date": {
      "$numberLong": "1673164855000"
    }
  },
  "strategy": "Trend from seasonal decompositon",
  "symbol": "SOL"
},{
  "side": "BUY",
  "price": 13.883,
  "timestamp": {
    "$date": {
      "$numberLong": "1673193654000"
    }
  },
  "strategy": "Trend from seasonal decompositon",
  "symbol": "SOL"
},{
  "side": "SELL",
  "price": 16.417,
  "timestamp": {
    "$date": {
      "$numberLong": "1673388054000"
    }
  },
  "strategy": "Trend from seasonal decompositon",
  "symbol": "SOL"
},{
  "side": "BUY",
  "price": 15.825,
  "timestamp": {
    "$date": {
      "$numberLong": "1673535654000"
    }
  },
  "strategy": "Trend from seasonal decompositon",
  "symbol": "SOL"
},{
  "side": "SELL",
  "price": 22.965,
  "timestamp": {
    "$date": {
      "$numberLong": "1674028854000"
    }
  },
  "strategy": "Trend from seasonal decompositon",
  "symbol": "SOL"
},{
  "side": "BUY",
  "price": 21.406,
  "timestamp": {
    "$date": {
      "$numberLong": "1674226856000"
    }
  },
  "strategy": "Trend from seasonal decompositon",
  "symbol": "SOL"
},{
  "side": "SELL",
  "price": 24.666,
  "timestamp": {
    "$date": {
      "$numberLong": "1674457258000"
    }
  },
  "strategy": "Trend from seasonal decompositon",
  "symbol": "SOL"
},{
  "side": "BUY",
  "price": 24.453,
  "timestamp": {
    "$date": {
      "$numberLong": "1674565256000"
    }
  },
  "strategy": "Trend from seasonal decompositon",
  "symbol": "SOL"
},{
  "side": "SELL",
  "price": 22.526,
  "timestamp": {
    "$date": {
      "$numberLong": "1674612056000"
    }
  },
  "strategy": "Trend from seasonal decompositon",
  "symbol": "SOL"
},{
  "side": "BUY",
  "price": 24.592,
  "timestamp": {
    "$date": {
      "$numberLong": "1674716459000"
    }
  },
  "strategy": "Trend from seasonal decompositon",
  "symbol": "SOL"
},{
  "side": "SELL",
  "price": 23.65,
  "timestamp": {
    "$date": {
      "$numberLong": "1674817257000"
    }
  },
  "strategy": "Trend from seasonal decompositon",
  "symbol": "SOL"
},{
  "side": "BUY",
  "price": 24.344,
  "timestamp": {
    "$date": {
      "$numberLong": "1674892855000"
    }
  },
  "strategy": "Trend from seasonal decompositon",
  "symbol": "SOL"
},{
  "side": "SELL",
  "price": 24.163,
  "timestamp": {
    "$date": {
      "$numberLong": "1674972055000"
    }
  },
  "strategy": "Trend from seasonal decompositon",
  "symbol": "SOL"
},{
  "side": "BUY",
  "price": 26.03,
  "timestamp": {
    "$date": {
      "$numberLong": "1675026054000"
    }
  },
  "strategy": "Trend from seasonal decompositon",
  "symbol": "SOL"
},{
  "side": "SELL",
  "price": 24.111,
  "timestamp": {
    "$date": {
      "$numberLong": "1675152056000"
    }
  },
  "strategy": "Trend from seasonal decompositon",
  "symbol": "SOL"
},{
  "side": "BUY",
  "price": 23.32,
  "timestamp": {
    "$date": {
      "$numberLong": "1675242055000"
    }
  },
  "strategy": "Trend from seasonal decompositon",
  "symbol": "SOL"
},{
  "side": "SELL",
  "price": 23.459,
  "timestamp": {
    "$date": {
      "$numberLong": "1675249255000"
    }
  },
  "strategy": "Trend from seasonal decompositon",
  "symbol": "SOL"
},{
  "side": "BUY",
  "price": 24.841,
  "timestamp": {
    "$date": {
      "$numberLong": "1675324856000"
    }
  },
  "strategy": "Trend from seasonal decompositon",
  "symbol": "SOL"
},{
  "side": "SELL",
  "price": 24.578,
  "timestamp": {
    "$date": {
      "$numberLong": "1675429256000"
    }
  },
  "strategy": "Trend from seasonal decompositon",
  "symbol": "SOL"
},{
  "side": "BUY",
  "price": 24.583,
  "timestamp": {
    "$date": {
      "$numberLong": "1675512053000"
    }
  },
  "strategy": "Trend from seasonal decompositon",
  "symbol": "SOL"
},{
  "side": "SELL",
  "price": 24.405,
  "timestamp": {
    "$date": {
      "$numberLong": "1675587656000"
    }
  },
  "strategy": "Trend from seasonal decompositon",
  "symbol": "SOL"
},{
  "side": "BUY",
  "price": 23.673,
  "timestamp": {
    "$date": {
      "$numberLong": "1675792850000"
    }
  },
  "strategy": "Trend from seasonal decompositon",
  "symbol": "SOL"
},{
  "side": "BUY",
  "price": 23.95,
  "timestamp": {
    "$date": {
      "$numberLong": "1675821656000"
    }
  },
  "strategy": "Trend from seasonal decompositon",
  "symbol": "SOL"
},{
  "side": "SELL",
  "price": 22.537,
  "timestamp": {
    "$date": {
      "$numberLong": "1675918856000"
    }
  },
  "strategy": "Trend from seasonal decompositon",
  "symbol": "SOL"
}]